{
  "indexes": [
    {
      "collectionGroup": "transactions",
      "queryScope": "COLLECTION",
      "fields": [
        {
          "fieldPath": "time",
          "order": "ASCENDING"
        },
        {
          "fieldPath": "type",
          "order": "ASCENDING"
        }
      ]
    },
    {
      "collectionGroup": "transactions",
      "queryScope": "COLLECTION",
      "fields": [
        {
          "fieldPath": "time",
          "order": "ASCENDING"
        },
        {
          "fieldPath": "type",
          "order": "ASCENDING"
        },
        {
          "fieldPath": "category",
          "order": "ASCENDING"
        }
      ]
    },
    {
      "collectionGroup": "transactions",
      "queryScope": "COLLECTION",
      "fields": [
        {
          "fieldPath": "time",
          "order": "ASCENDING"
        },
        {
          "fieldPath": "amount",
          "order": "DESCENDING"
        }
      ]
    },
    {
      "collectionGroup": "transactions",
      "queryScope": "COLLECTION",
      "fields": [
        {
          "fieldPath": "time",
          "order": "ASCENDING"
        },
        {
          "fieldPath": "type",
          "order": "ASCENDING"
        },
        {
          "fieldPath": "amount",
          "order": "DESCENDING"
        }
      ]
    },
    {
      "collectionGroup": "transactions",
      "queryScope": "COLLECTION",
      "fields": [
        {
          "fieldPath": "type",
          "order": "ASCENDING"
        },
        {
          "fieldPath": "category",
          "order": "ASCENDING"
        },
        {
          "fieldPath": "time",
          "order": "ASCENDING"
        },
        {
          "fieldPath": "amount",
          "order": "DESCENDING"
        }
      ]
    },
    {
      "collectionGroup": "transactions",
      "queryScope": "COLLECTION",
      "fields": [
        {
          "fieldPath": "type",
          "order": "ASCENDING"
        },
        {
          "fieldPath": "time",
          "order": "ASCENDING"
        },
        {
          "fieldPath": "amount",
          "order": "ASCENDING"
        }
      ]
    },
    {
      "collectionGroup": "transactions",
      "queryScope": "COLLECTION",
      "fields": [
        {
          "fieldPath": "category",
          "order": "ASCENDING"
        },
        {
          "fieldPath": "time",
          "order": "DESCENDING"
        }
      ]
    },
    {
      "collectionGroup": "transactions",
      "queryScope": "COLLECTION",
      "fields": [
        {
          "fieldPath": "category",
          "order": "ASCENDING"
        },
        {
          "fieldPath": "type",
          "order": "ASCENDING"
        },
        {
          "fieldPath": "time",
          "order": "ASCENDING"
        },
        {
          "fieldPath": "amount",
          "order": "ASCENDING"
        }
      ]
    }
  ],
  "fieldOverrides": []
}
